rigelcore/__init__.py
rigelcore/clients/__init__.py
rigelcore/clients/docker.py
rigelcore/clients/rosbridge.py
rigelcore/exceptions.py
rigelcore/loggers/__init__.py
rigelcore/loggers/error.py
rigelcore/loggers/message.py
rigelcore/models/__init__.py
rigelcore/models/builder.py
rigelcore/py.typed
rigelcore/simulations/__init__.py
rigelcore/simulations/callback.py
rigelcore/simulations/command.py
rigelcore/simulations/parser.py
rigelcore/simulations/requirements/__init__.py
rigelcore/simulations/requirements/absence.py
rigelcore/simulations/requirements/disjoint.py
rigelcore/simulations/requirements/existence.py
rigelcore/simulations/requirements/manager.py
rigelcore/simulations/requirements/node.py
rigelcore/simulations/requirements/prevention.py
rigelcore/simulations/requirements/requirement.py
rigelcore/simulations/requirements/response.py
rigelcore/simulations/requirements/simple.py
rigelcore/simulations/strategy.py
rigelcore-0.1.21.dist-info/LICENSE.md
rigelcore-0.1.21.dist-info/WHEEL
rigelcore-0.1.21.dist-info/METADATA
rigelcore-0.1.21.dist-info/RECORD
