Metadata-Version: 2.1
Name: rigelcore
Version: 0.1.21
Summary: A common interface for Rigel and all its plugins.
Home-page: https://github.com/rigel-ros/rigelcore
License: MIT
Keywords: docker,ros,cloud,robotics
Author: Pedro Miguel Melo
Author-email: pedro.m.melo@inesctec.pt
Maintainer: Pedro Miguel Melo
Maintainer-email: pedro.m.melo@inesctec.pt
Requires-Python: >=3.8,<4.0
Classifier: Intended Audience :: Developers
Classifier: License :: OSI Approved :: MIT License
Classifier: Operating System :: POSIX
Classifier: Programming Language :: Python :: 3
Classifier: Programming Language :: Python :: 3 :: Only
Classifier: Programming Language :: Python :: 3.10
Classifier: Programming Language :: Python :: 3.8
Classifier: Programming Language :: Python :: 3.9
Requires-Dist: pydantic (>=1.9.0,<2.0.0)
Requires-Dist: python-on-whales (>=0.50.0,<0.51.0)
Requires-Dist: rich (>=11.2.0,<12.0.0)
Requires-Dist: rigel-hpl (>=0.1.0,<0.2.0)
Requires-Dist: roslibpy (>=1.3.0,<2.0.0)
Project-URL: Repository, https://github.com/rigel-ros/rigelcore
